game_prediction2/__init__.py
game_prediction2/__init__.pyi
game_prediction2/main.py
game_prediction2/manual.py
game_prediction2/types.py
game_prediction2/beam/__init__.py
game_prediction2/beam/__init__.pyi
game_prediction2/beam/decoding.py
game_prediction2/beam/predict.py
game_prediction2/beam/searching.py
game_prediction2/beam/succs.py
game_prediction2/util/__init__.py
game_prediction2/util/__init__.pyi
game_prediction2/util/aggregate.py
game_prediction2/util/logprobs.py
game_prediction2/util/predict.py
game_prediction2-0.2.2.dist-info/METADATA
game_prediction2-0.2.2.dist-info/WHEEL
game_prediction2-0.2.2.dist-info/top_level.txt
game_prediction2-0.2.2.dist-info/RECORD
